pycgnat/__init__.py
pycgnat/__main__.py
pycgnat/settings.py
pycgnat/generator/__init__.py
pycgnat/generator/routeros.py
pycgnat/translator/__init__.py
pycgnat/translator/direct.py
pycgnat/translator/reverse.py
pycgnat/utils/__init__.py
pycgnat/utils/parser.py
pycgnat/utils/vlsm.py
pycgnat-1.0.0.dist-info/LICENSE
pycgnat-1.0.0.dist-info/METADATA
pycgnat-1.0.0.dist-info/WHEEL
pycgnat-1.0.0.dist-info/entry_points.txt
pycgnat-1.0.0.dist-info/top_level.txt
pycgnat-1.0.0.dist-info/RECORD
