Metadata-Version: 2.1
Name: pycgnat
Version: 1.0.0
Summary: Python module for generating CGNAT rules using netmap
Home-page: https://github.com/williamabreu/py-cgnat
Author: William Abreu
Author-email: contato@williamabreu.net
License: MIT License
Keywords: netmap cgnat rfc6598 routeros
Platform: any
Classifier: Environment :: Console
Classifier: Intended Audience :: System Administrators
Classifier: Programming Language :: Python :: 3 :: Only
Classifier: License :: OSI Approved :: MIT License
Classifier: Operating System :: OS Independent
Classifier: Topic :: Software Development :: Libraries :: Python Modules
Classifier: Topic :: System :: Networking :: Firewalls
Classifier: Topic :: Utilities
Requires-Python: >=3.7
License-File: LICENSE
